[
  {
    "model_name": "q_model_0425_2023.pkl",
    "episodes": 1000,
    "epsilon": 0.9,
    "alpha": 0.1,
    "gamma": 0.95,
    "roi": -0.17654028436018956,
    "hit_rate": 0.41172985781990523,
    "total_reward": -1490,
    "max_drawdown": 1499,
    "timestamp": "2025-04-25T20:24:02.660044"
  },
  {
    "model_name": "q_model_0425_2027.pkl",
    "episodes": 1000,
    "epsilon": 0.9,
    "alpha": 0.1,
    "gamma": 0.95,
    "roi": 0.48732614064734175,
    "hit_rate": 0.7436630703236708,
    "total_reward": 7498,
    "max_drawdown": 11,
    "timestamp": "2025-04-25T20:27:16.806561"
  },
  {
    "model_name": "q_model_0425_2027.pkl",
    "episodes": 1000,
    "epsilon": 0.9,
    "alpha": 0.1,
    "gamma": 0.95,
    "roi": 0.5072445665750687,
    "hit_rate": 0.7536222832875343,
    "total_reward": 8122,
    "max_drawdown": 9,
    "timestamp": "2025-04-25T20:27:29.796501"
  },
  {
    "model_name": "q_model_0425_2057.pkl",
    "episodes": 1000,
    "epsilon": 0.9,
    "alpha": 0.1,
    "gamma": 0.95,
    "roi": 0.5201195963622773,
    "hit_rate": 0.7600597981811387,
    "total_reward": 8350,
    "max_drawdown": 15,
    "timestamp": "2025-04-25T21:00:07.646909"
  },
  {
    "model_name": "q_model_0425_2057.pkl",
    "episodes": 1000,
    "epsilon": 0.5,
    "alpha": 0.1,
    "gamma": 0.95,
    "roi": 0.5121005565630667,
    "hit_rate": 0.7560502782815334,
    "total_reward": 8189,
    "max_drawdown": 7,
    "timestamp": "2025-04-25T21:00:17.944902"
  },
  {
    "model_name": "q_model_0425_2057.pkl",
    "episodes": 1000,
    "epsilon": 0.8,
    "alpha": 0.1,
    "gamma": 0.95,
    "roi": 0.5120606478290833,
    "hit_rate": 0.7560303239145417,
    "total_reward": 8173,
    "max_drawdown": 10,
    "timestamp": "2025-04-25T21:00:28.784999"
  },
  {
    "model_name": "q_model_0425_2057.pkl",
    "episodes": 1000,
    "epsilon": 0.9,
    "alpha": 0.5,
    "gamma": 0.95,
    "roi": 0.5190375790648641,
    "hit_rate": 0.7595187895324321,
    "total_reward": 8370,
    "max_drawdown": 7,
    "timestamp": "2025-04-25T21:01:08.116784"
  },
  {
    "model_name": "q_model_0425_2057.pkl",
    "episodes": 1000,
    "epsilon": 0.9,
    "alpha": 0.2,
    "gamma": 0.95,
    "roi": 0.5051755890010796,
    "hit_rate": 0.7525877945005398,
    "total_reward": 7955,
    "max_drawdown": 11,
    "timestamp": "2025-04-25T21:01:18.858257"
  },
  {
    "model_name": "q_model_0425_2057.pkl",
    "episodes": 1000,
    "epsilon": 0.9,
    "alpha": 0.1,
    "gamma": 0.8,
    "roi": 0.5150484825588717,
    "hit_rate": 0.7575242412794359,
    "total_reward": 8180,
    "max_drawdown": 10,
    "timestamp": "2025-04-25T21:01:43.166750"
  },
  {
    "model_name": "q_model_0425_2057.pkl",
    "episodes": 1000,
    "epsilon": 0.9,
    "alpha": 0.1,
    "gamma": 0.1,
    "roi": 0.5128060617446302,
    "hit_rate": 0.7564030308723151,
    "total_reward": 8189,
    "max_drawdown": 8,
    "timestamp": "2025-04-25T21:01:54.414713"
  },
  {
    "model_name": "q_model_0425_2102.pkl",
    "episodes": 1000,
    "epsilon": 0.9,
    "alpha": 0.1,
    "gamma": 0.5,
    "roi": 0.5211740563397799,
    "hit_rate": 0.7605870281698899,
    "total_reward": 8381,
    "max_drawdown": 12,
    "timestamp": "2025-04-25T21:02:26.479105"
  },
  {
    "model_name": "q_model_0425_2103.pkl",
    "episodes": 5000,
    "epsilon": 0.9,
    "alpha": 0.1,
    "gamma": 0.95,
    "roi": 0.5199244523416047,
    "hit_rate": 0.7599622261708023,
    "total_reward": 41843,
    "max_drawdown": 11,
    "timestamp": "2025-04-25T21:06:17.033867"
  },
  {
    "model_name": "q_model_0425_2201.pkl",
    "episodes": 5000,
    "epsilon": 0.9,
    "alpha": 0.1,
    "gamma": 0.95,
    "roi": 0.5122620220180284,
    "hit_rate": 0.7561310110090141,
    "total_reward": 41087,
    "max_drawdown": 8,
    "timestamp": "2025-04-25T22:01:34.853457"
  },
  {
    "model_name": "q_model_0425_2202.pkl",
    "episodes": 5000,
    "epsilon": 0.9,
    "alpha": 0.1,
    "gamma": 0.95,
    "roi": 0.5179535788672844,
    "hit_rate": 0.7589767894336422,
    "total_reward": 41529,
    "max_drawdown": 12,
    "timestamp": "2025-04-25T22:03:00.009724"
  },
  {
    "model_name": "q_model_0425_2214.pkl",
    "episodes": 1000,
    "epsilon": 0.9,
    "alpha": 0.1,
    "gamma": 0.95,
    "roi": 0.0001269035532994924,
    "hit_rate": 0.750253807106599,
    "total_reward": 2,
    "max_drawdown": 31,
    "timestamp": "2025-04-25T22:14:50.642087"
  },
  {
    "model_name": "q_model_0425_2214.pkl",
    "episodes": 1000,
    "epsilon": 0.9,
    "alpha": 0.1,
    "gamma": 0.95,
    "roi": 0.001005530417295123,
    "hit_rate": 0.7586726998491704,
    "total_reward": 16,
    "max_drawdown": 29,
    "timestamp": "2025-04-25T22:15:00.116122"
  },
  {
    "model_name": "q_model_0425_2214.pkl",
    "episodes": 1000,
    "epsilon": 0.9,
    "alpha": 0.1,
    "gamma": 0.95,
    "roi": -0.00012670256572695597,
    "hit_rate": 0.7507127019322142,
    "total_reward": -2,
    "max_drawdown": 30,
    "timestamp": "2025-04-25T22:15:03.233200"
  },
  {
    "model_name": "q_model_0425_2214.pkl",
    "episodes": 1000,
    "epsilon": 0.9,
    "alpha": 0.1,
    "gamma": 0.95,
    "roi": 0.0002472035102898461,
    "hit_rate": 0.7586675730795377,
    "total_reward": 4,
    "max_drawdown": 31,
    "timestamp": "2025-04-25T22:15:12.007656"
  },
  {
    "model_name": "q_model_0425_2214.pkl",
    "episodes": 1000,
    "epsilon": 0.9,
    "alpha": 0.1,
    "gamma": 0.95,
    "roi": 0.00012656625743576763,
    "hit_rate": 0.7526262498417922,
    "total_reward": 2,
    "max_drawdown": 30,
    "timestamp": "2025-04-25T22:15:18.217456"
  },
  {
    "model_name": "q_model_0425_2214.pkl",
    "episodes": 2000,
    "epsilon": 0.9,
    "alpha": 0.1,
    "gamma": 0.95,
    "roi": 0.00024975804689207333,
    "hit_rate": 0.7557366301395523,
    "total_reward": 8,
    "max_drawdown": 32,
    "timestamp": "2025-04-25T22:15:59.966500"
  },
  {
    "model_name": "q_model_0425_2217.pkl",
    "episodes": 1000,
    "epsilon": 0.9,
    "alpha": 0.1,
    "gamma": 0.95,
    "roi": 0.01110357164888039,
    "hit_rate": 0.7544876935414225,
    "total_reward": 180,
    "max_drawdown": 580,
    "timestamp": "2025-04-25T22:17:04.254723"
  },
  {
    "model_name": "q_model_0425_2217.pkl",
    "episodes": 5000,
    "epsilon": 0.9,
    "alpha": 0.1,
    "gamma": 0.95,
    "roi": 0.003979060195720023,
    "hit_rate": 0.7548774573805349,
    "total_reward": 320,
    "max_drawdown": 640,
    "timestamp": "2025-04-25T22:17:30.612908"
  },
  {
    "model_name": "q_model_0429_1012.pkl",
    "episodes": 1000,
    "epsilon": 0.9,
    "alpha": 0.1,
    "gamma": 0.95,
    "roi": -0.02,
    "hit_rate": 0.0,
    "total_reward": -100,
    "max_drawdown": 100,
    "timestamp": "2025-04-29T10:12:40.625286"
  },
  {
    "model_name": "q_model_0429_1012.pkl",
    "episodes": 1,
    "epsilon": 0.9,
    "alpha": 0.1,
    "gamma": 0.95,
    "roi": -20.0,
    "hit_rate": 0.0,
    "total_reward": -100,
    "max_drawdown": 100,
    "timestamp": "2025-04-29T10:13:02.407733"
  },
  {
    "model_name": "q_model_0429_1012.pkl",
    "episodes": 10,
    "epsilon": 0.9,
    "alpha": 0.1,
    "gamma": 0.95,
    "roi": -2.0,
    "hit_rate": 0.0,
    "total_reward": -100,
    "max_drawdown": 100,
    "timestamp": "2025-04-29T10:13:06.515503"
  },
  {
    "model_name": "q_model_0429_1012.pkl",
    "episodes": 100,
    "epsilon": 0.9,
    "alpha": 0.1,
    "gamma": 0.95,
    "roi": -0.2,
    "hit_rate": 0.0,
    "total_reward": -100,
    "max_drawdown": 100,
    "timestamp": "2025-04-29T10:13:10.249395"
  },
  {
    "model_name": "q_model_0429_1012.pkl",
    "episodes": 1000,
    "epsilon": 0.9,
    "alpha": 0.1,
    "gamma": 0.95,
    "roi": -0.02,
    "hit_rate": 0.0,
    "total_reward": -100,
    "max_drawdown": 100,
    "timestamp": "2025-04-29T10:13:15.418635"
  },
  {
    "model_name": "q_model_0429_1122.pkl",
    "episodes": 1000,
    "epsilon": 0.9,
    "alpha": 0.1,
    "gamma": 0.95,
    "roi": -0.02,
    "hit_rate": 0.0,
    "total_reward": -100,
    "max_drawdown": 100,
    "timestamp": "2025-04-29T11:22:21.411424"
  },
  {
    "model_name": "q_model_0429_1122.pkl",
    "episodes": 10,
    "epsilon": 0.9,
    "alpha": 0.1,
    "gamma": 0.95,
    "roi": -2.0,
    "hit_rate": 0.0,
    "total_reward": -100,
    "max_drawdown": 100,
    "timestamp": "2025-04-29T11:22:34.235947"
  },
  {
    "model_name": "q_model_0429_1124.pkl",
    "episodes": 1,
    "epsilon": 0.9,
    "alpha": 0.1,
    "gamma": 0.95,
    "roi": -20.0,
    "hit_rate": 0.0,
    "total_reward": -100,
    "max_drawdown": 100,
    "timestamp": "2025-04-29T11:24:57.063811"
  },
  {
    "model_name": "q_model_0429_1124.pkl",
    "episodes": 10,
    "epsilon": 0.9,
    "alpha": 0.1,
    "gamma": 0.95,
    "roi": -2.0,
    "hit_rate": 0.0,
    "total_reward": -100,
    "max_drawdown": 100,
    "timestamp": "2025-04-29T11:25:03.607770"
  },
  {
    "model_name": "q_model_0429_1124.pkl",
    "episodes": 30,
    "epsilon": 0.9,
    "alpha": 0.1,
    "gamma": 0.95,
    "roi": -0.6666666666666666,
    "hit_rate": 0.0,
    "total_reward": -100,
    "max_drawdown": 100,
    "timestamp": "2025-04-29T11:25:07.548865"
  },
  {
    "model_name": "q_model_0429_1133.pkl",
    "episodes": 1,
    "epsilon": 0.9,
    "alpha": 0.1,
    "gamma": 0.95,
    "roi": -20.0,
    "hit_rate": 0.0,
    "total_reward": -100,
    "max_drawdown": 100,
    "timestamp": "2025-04-29T11:33:23.300627"
  },
  {
    "model_name": "q_model_0429_1133.pkl",
    "episodes": 1,
    "epsilon": 0.9,
    "alpha": 0.1,
    "gamma": 0.95,
    "roi": -20.0,
    "hit_rate": 0.0,
    "total_reward": -100,
    "max_drawdown": 100,
    "timestamp": "2025-04-29T11:33:32.278397"
  },
  {
    "model_name": "q_model_0429_1133.pkl",
    "episodes": 10,
    "epsilon": 0.9,
    "alpha": 0.1,
    "gamma": 0.95,
    "roi": -2.0,
    "hit_rate": 0.0,
    "total_reward": -100,
    "max_drawdown": 100,
    "timestamp": "2025-04-29T11:33:37.619969"
  },
  {
    "model_name": "q_model_0429_1137.pkl",
    "episodes": 1,
    "epsilon": 0.9,
    "alpha": 0.1,
    "gamma": 0.95,
    "roi": -20.0,
    "hit_rate": 0.0,
    "total_reward": -100,
    "max_drawdown": 100,
    "timestamp": "2025-04-29T11:37:40.553902"
  },
  {
    "model_name": "q_model_0429_1138.pkl",
    "episodes": 1,
    "epsilon": 0.9,
    "alpha": 0.1,
    "gamma": 0.95,
    "roi": -20.0,
    "hit_rate": 0.0,
    "total_reward": -100,
    "max_drawdown": 100,
    "timestamp": "2025-04-29T11:38:36.453048"
  },
  {
    "model_name": "q_model_0429_1138.pkl",
    "episodes": 100,
    "epsilon": 0.9,
    "alpha": 0.1,
    "gamma": 0.95,
    "roi": -0.2,
    "hit_rate": 0.0,
    "total_reward": -100,
    "max_drawdown": 100,
    "timestamp": "2025-04-29T11:38:40.682167"
  },
  {
    "model_name": "q_model_0429_1138.pkl",
    "episodes": 1000,
    "epsilon": 0.9,
    "alpha": 0.1,
    "gamma": 0.95,
    "roi": -0.02,
    "hit_rate": 0.0,
    "total_reward": -100,
    "max_drawdown": 100,
    "timestamp": "2025-04-29T11:38:44.405036"
  },
  {
    "model_name": "q_model_0429_1140.pkl",
    "episodes": 1000,
    "epsilon": 0.9,
    "alpha": 0.1,
    "gamma": 0.95,
    "roi": -0.02,
    "hit_rate": 0.0,
    "total_reward": -100,
    "max_drawdown": 100,
    "timestamp": "2025-04-29T11:40:47.619377"
  },
  {
    "model_name": "q_model_0429_1140.pkl",
    "episodes": 1000,
    "epsilon": 0.9,
    "alpha": 0.1,
    "gamma": 0.95,
    "roi": -0.02,
    "hit_rate": 0.0,
    "total_reward": -100,
    "max_drawdown": 100,
    "timestamp": "2025-04-29T11:40:53.716191"
  },
  {
    "model_name": "q_model_0429_1141.pkl",
    "episodes": 1000,
    "epsilon": 0.9,
    "alpha": 0.1,
    "gamma": 0.95,
    "roi": -0.02,
    "hit_rate": 0.0,
    "total_reward": -100,
    "max_drawdown": 100,
    "timestamp": "2025-04-29T11:41:48.052828"
  },
  {
    "model_name": "q_model_0429_1143.pkl",
    "episodes": 10,
    "epsilon": 0.9,
    "alpha": 0.1,
    "gamma": 0.95,
    "roi": -2.0,
    "hit_rate": 0.0,
    "total_reward": -100,
    "max_drawdown": 100,
    "timestamp": "2025-04-29T11:43:25.263399"
  },
  {
    "model_name": "q_model_0429_1145.pkl",
    "episodes": 1000,
    "epsilon": 0.9,
    "alpha": 0.1,
    "gamma": 0.95,
    "roi": -0.02,
    "hit_rate": 0.0,
    "total_reward": -100,
    "max_drawdown": 100,
    "timestamp": "2025-04-29T11:45:04.756387"
  },
  {
    "model_name": "q_model_0429_1145.pkl",
    "episodes": 5000,
    "epsilon": 0.9,
    "alpha": 0.1,
    "gamma": 0.95,
    "roi": -0.004,
    "hit_rate": 0.0,
    "total_reward": -100,
    "max_drawdown": 100,
    "timestamp": "2025-04-29T11:46:04.905445"
  },
  {
    "model_name": "q_model_0429_1145.pkl",
    "episodes": 5000,
    "epsilon": 0.9,
    "alpha": 0.1,
    "gamma": 0.95,
    "roi": -0.004,
    "hit_rate": 0.0,
    "total_reward": -100,
    "max_drawdown": 100,
    "timestamp": "2025-04-29T11:46:23.076374"
  },
  {
    "model_name": "q_model_0429_1149.pkl",
    "episodes": 1000,
    "epsilon": 0.9,
    "alpha": 0.1,
    "gamma": 0.95,
    "roi": -0.02,
    "hit_rate": 0.0,
    "total_reward": -100,
    "max_drawdown": 100,
    "timestamp": "2025-04-29T11:49:36.287693"
  },
  {
    "model_name": "q_model_0429_1149.pkl",
    "episodes": 10000,
    "epsilon": 0.9,
    "alpha": 0.1,
    "gamma": 0.95,
    "roi": -0.002,
    "hit_rate": 0.0,
    "total_reward": -100,
    "max_drawdown": 100,
    "timestamp": "2025-04-29T11:49:48.153388"
  },
  {
    "model_name": "q_model_0429_1149.pkl",
    "episodes": 10000,
    "epsilon": 0.9,
    "alpha": 0.3,
    "gamma": 0.95,
    "roi": -0.002,
    "hit_rate": 0.0,
    "total_reward": -100,
    "max_drawdown": 100,
    "timestamp": "2025-04-29T11:50:26.706313"
  },
  {
    "model_name": "q_model_0429_1155.pkl",
    "episodes": 1000,
    "epsilon": 0.9,
    "alpha": 0.1,
    "gamma": 0.95,
    "roi": -0.02,
    "hit_rate": 0.0,
    "total_reward": -100,
    "max_drawdown": 100,
    "timestamp": "2025-04-29T11:55:59.609471"
  },
  {
    "model_name": "q_model_0429_1155.pkl",
    "episodes": 100000,
    "epsilon": 0.9,
    "alpha": 0.1,
    "gamma": 0.95,
    "roi": -0.0002,
    "hit_rate": 0.0,
    "total_reward": -100,
    "max_drawdown": 100,
    "timestamp": "2025-04-29T11:57:02.823589"
  },
  {
    "model_name": "q_model_0429_1207.pkl",
    "episodes": 1000,
    "epsilon": 0.9,
    "alpha": 0.1,
    "gamma": 0.95,
    "roi": -0.02,
    "hit_rate": 0.0,
    "total_reward": -100,
    "max_drawdown": 100,
    "timestamp": "2025-04-29T12:07:54.001955"
  },
  {
    "model_name": "q_model_0429_1214.pkl",
    "episodes": 1000,
    "epsilon": 0.9,
    "alpha": 0.1,
    "gamma": 0.95,
    "roi": -0.02,
    "hit_rate": 0.0,
    "total_reward": -100,
    "max_drawdown": 100,
    "timestamp": "2025-04-29T12:14:28.301585"
  },
  {
    "model_name": "q_model_0429_1215.pkl",
    "episodes": 1000,
    "epsilon": 0.9,
    "alpha": 0.1,
    "gamma": 0.95,
    "roi": -0.02,
    "hit_rate": 0.0,
    "total_reward": -100,
    "max_drawdown": 100,
    "timestamp": "2025-04-29T12:15:50.251679"
  },
  {
    "model_name": "q_model_0429_1219.pkl",
    "episodes": 1000,
    "epsilon": 0.9,
    "alpha": 0.1,
    "gamma": 0.95,
    "roi": -0.02,
    "hit_rate": 0.0,
    "total_reward": -100,
    "max_drawdown": 100,
    "timestamp": "2025-04-29T12:19:13.430572"
  },
  {
    "model_name": "q_model_0429_1221.pkl",
    "episodes": 1000,
    "epsilon": 0.9,
    "alpha": 0.1,
    "gamma": 0.95,
    "roi": -0.02,
    "hit_rate": 0.0,
    "total_reward": -100,
    "max_drawdown": 100,
    "timestamp": "2025-04-29T12:21:38.381002"
  },
  {
    "model_name": "q_model_0429_1221.pkl",
    "episodes": 10000,
    "epsilon": 0.9,
    "alpha": 0.1,
    "gamma": 0.95,
    "roi": -0.002,
    "hit_rate": 0.0,
    "total_reward": -100,
    "max_drawdown": 100,
    "timestamp": "2025-04-29T12:21:48.791552"
  },
  {
    "model_name": "q_model_0429_1221.pkl",
    "episodes": 10000,
    "epsilon": 0.9,
    "alpha": 0.1,
    "gamma": 0.95,
    "roi": -0.002,
    "hit_rate": 0.0,
    "total_reward": -100,
    "max_drawdown": 100,
    "timestamp": "2025-04-29T12:22:10.189575"
  },
  {
    "model_name": "q_model_0429_1223.pkl",
    "episodes": 1000,
    "epsilon": 0.9,
    "alpha": 0.1,
    "gamma": 0.95,
    "roi": -0.02,
    "hit_rate": 0.0,
    "total_reward": -100,
    "max_drawdown": 100,
    "timestamp": "2025-04-29T12:23:02.831989"
  },
  {
    "model_name": "q_model_0429_1223.pkl",
    "episodes": 10000,
    "epsilon": 0.9,
    "alpha": 0.1,
    "gamma": 0.95,
    "roi": 0.0,
    "hit_rate": 0.0,
    "total_reward": 0,
    "max_drawdown": 0,
    "timestamp": "2025-04-29T12:23:20.710326"
  },
  {
    "model_name": "q_model_0429_1223.pkl",
    "episodes": 10000,
    "epsilon": 0.9,
    "alpha": 0.1,
    "gamma": 0.95,
    "roi": 0.0,
    "hit_rate": 0.0,
    "total_reward": 0,
    "max_drawdown": 0,
    "timestamp": "2025-04-29T12:23:26.633035"
  },
  {
    "model_name": "q_model_0429_1223.pkl",
    "episodes": 100,
    "epsilon": 0.9,
    "alpha": 0.1,
    "gamma": 0.95,
    "roi": -0.2,
    "hit_rate": 0.0,
    "total_reward": -100,
    "max_drawdown": 100,
    "timestamp": "2025-04-29T12:23:30.409649"
  },
  {
    "model_name": "q_model_0429_1223.pkl",
    "episodes": 1000,
    "epsilon": 0.9,
    "alpha": 0.1,
    "gamma": 0.95,
    "roi": -0.02,
    "hit_rate": 0.0,
    "total_reward": -100,
    "max_drawdown": 100,
    "timestamp": "2025-04-29T12:24:20.219064"
  },
  {
    "model_name": "q_model_0429_1230.pkl",
    "episodes": 1000,
    "epsilon": 0.9,
    "alpha": 0.1,
    "gamma": 0.95,
    "roi": 0.0037507032568606614,
    "hit_rate": 0.7517659561167719,
    "total_reward": 60,
    "max_drawdown": 600,
    "timestamp": "2025-04-29T12:31:05.447344"
  },
  {
    "model_name": "out_test.pkl",
    "episodes": 1000,
    "epsilon": 0.9,
    "alpha": 0.1,
    "gamma": 0.95,
    "roi": 0.01733424131740234,
    "hit_rate": 0.7586825976598774,
    "total_reward": 280,
    "max_drawdown": 600,
    "timestamp": "2025-04-29T12:32:20.289015"
  },
  {
    "model_name": "aaaaaaaaa.pkl",
    "episodes": 1000,
    "epsilon": 0.9,
    "alpha": 0.1,
    "gamma": 0.95,
    "roi": 0.009941593140300733,
    "hit_rate": 0.7565552379768858,
    "total_reward": 160,
    "max_drawdown": 600,
    "timestamp": "2025-04-29T12:33:08.818213"
  },
  {
    "model_name": "q_model_0429_1234.pkl",
    "episodes": 1000,
    "epsilon": 0.9,
    "alpha": 0.1,
    "gamma": 0.95,
    "roi": 0.014967259120673527,
    "hit_rate": 0.7597131275335204,
    "total_reward": 240,
    "max_drawdown": 580,
    "timestamp": "2025-04-29T12:34:38.703721"
  },
  {
    "model_name": "1111111111.pkl",
    "episodes": 1000,
    "epsilon": 0.9,
    "alpha": 0.1,
    "gamma": 0.95,
    "roi": -0.0012438584489085141,
    "hit_rate": 0.7583183033770757,
    "total_reward": -20,
    "max_drawdown": 600,
    "timestamp": "2025-04-29T12:35:44.411319"
  },
  {
    "model_name": "q_model_0429_1236.pkl",
    "episodes": 1000,
    "epsilon": 0.9,
    "alpha": 0.1,
    "gamma": 0.95,
    "roi": -0.003755163349605708,
    "hit_rate": 0.7542245587683064,
    "total_reward": -60,
    "max_drawdown": 600,
    "timestamp": "2025-04-29T12:36:47.917244"
  },
  {
    "model_name": "q_model_0429_1237.pkl",
    "episodes": 1000,
    "epsilon": 0.9,
    "alpha": 0.1,
    "gamma": 0.95,
    "roi": 0.021256642700844014,
    "hit_rate": 0.7553610503282275,
    "total_reward": 340,
    "max_drawdown": 600,
    "timestamp": "2025-04-29T12:37:45.831806"
  },
  {
    "model_name": "q_model_0429_1238.pkl",
    "episodes": 1000,
    "epsilon": 0.9,
    "alpha": 0.1,
    "gamma": 0.95,
    "roi": 0.016131033627000867,
    "hit_rate": 0.7531951855068867,
    "total_reward": 260,
    "max_drawdown": 620,
    "timestamp": "2025-04-29T12:38:14.237189"
  },
  {
    "model_name": "11111.pkl",
    "episodes": 1000,
    "epsilon": 0.9,
    "alpha": 0.1,
    "gamma": 0.95,
    "roi": 0.009884475196145055,
    "hit_rate": 0.7656143819114104,
    "total_reward": 160,
    "max_drawdown": 600,
    "timestamp": "2025-04-29T12:38:48.676798"
  },
  {
    "model_name": "1aaaa1111.pkl",
    "episodes": 1000,
    "epsilon": 0.9,
    "alpha": 0.1,
    "gamma": 0.95,
    "roi": -0.0012377769525931427,
    "hit_rate": 0.757395717291744,
    "total_reward": -20,
    "max_drawdown": 600,
    "timestamp": "2025-04-29T12:38:52.852300"
  }
]